patcha/__init__.py
patcha/bulk.py
patcha/cli.py
patcha/findings.py
patcha/logger.py
patcha/progress.py
patcha/reporting.py
patcha/reporting/__init__.py
patcha/reporting/report_generator.py
patcha/scanners/__init__.py
patcha/scanners/bandit_scanner.py
patcha/scanners/base_scanner.py
patcha/scanners/custom_pattern_scanner.py
patcha/scanners/nikto_scanner.py
patcha/scanners/semgrep_scanner.py
patcha/scanners/trivy_scanner.py
patcha/scanners/trufflehog_scanner.py
patcha/utils/__init__.py
patcha/utils/deduplication.py
patcha/utils/file_utils.py
patcha/utils/remediation.py
patcha/utils/sarif_converter.py
patcha/utils/scoring.py
patcha/utils/verification.py
patcha-0.2.2.dist-info/licenses/LICENSE
patcha-0.2.2.dist-info/METADATA
patcha-0.2.2.dist-info/WHEEL
patcha-0.2.2.dist-info/entry_points.txt
patcha-0.2.2.dist-info/top_level.txt
patcha-0.2.2.dist-info/RECORD
