Metadata-Version: 2.4
Name: patcha
Version: 0.2.2
Summary: A security scanner for code repositories
Home-page: https://github.com/AdarshB7/patcha-engine
Author: Patcha Team
Author-email: patchasec@gmail.com
License: MIT
Classifier: Development Status :: 3 - Alpha
Classifier: Intended Audience :: Developers
Classifier: Topic :: Security
Classifier: Programming Language :: Python :: 3
Classifier: Programming Language :: Python :: 3.8
Classifier: Programming Language :: Python :: 3.9
Classifier: Programming Language :: Python :: 3.10
Requires-Python: >=3.8
License-File: LICENSE
Requires-Dist: semgrep>=1.0.0
Requires-Dist: bandit>=1.7.0
Requires-Dist: truffleHog>=2.2.1
Requires-Dist: jinja2>=3.0.0
Requires-Dist: rich>=10.0.0
Requires-Dist: typer>=0.4.0
Requires-Dist: pyyaml>=6.0
Requires-Dist: requests>=2.25.0
Dynamic: author
Dynamic: author-email
Dynamic: classifier
Dynamic: home-page
Dynamic: license
Dynamic: license-file
Dynamic: requires-dist
Dynamic: requires-python
Dynamic: summary
